<?xml version="1.0" encoding="utf-8"?>
<template>
    <id>oncoming_traffic_on_road</id>
    <name>Движение по встречке</name>
    <description>По данному обращению вас могут вызвать в ГИБДД в качестве свидетеля.</description>
    <law_links>
        <law_link>
            <title>КоАП РФ Статья 12.16. Несоблюдение требований, предписанных дорожными знаками или разметкой проезжей части дороги</title>
            <link>http://www.consultant.ru/document/cons_doc_LAW_34661/423d650543917f5abe5c2480d6fb3fca332f9d22/</link>
        </law_link>
    </law_links>
    <fields>
        <field>
            <name>event_location</name>
            <hint>Укажите место нарушения*</hint>
            <value></value>
            <required_field>true</required_field>
            <visibility>visible</visibility>
        </field>
        <field>
            <name>appeal_text</name>
            <hint>Напишите номер транспортного средства, марку и цвет*</hint>
            <value></value>
            <required_field>true</required_field>
            <visibility>visible</visibility>
        </field>
    </fields>
    <text>
        %date_time%, по адресу: %address%, координаты: %coordinates%, %yandex_map_link%, мной были зафиксированы нарушения ПДД РФ 9.1(1) - 
        "Движение по полосе, предназначенной для встречного движения". Нарушитель, который выехал на 
        полосу, предназначенную для встречного движения ТС, создал аварийную ситуацию, а так же подверг опасности себя и остальных 
        участников дорожного движения. Описание транспортного средства нарушителя: %description%
        
        Согласно КоАП РФ Статья 28.1 поводом для возбуждения административного дела может являться: сообщения и заявления от физических лиц; так же, поводом может стать фотосъемка или видеозапись.
        1. Установить водителя данного транспортного средства и привлечь его к административной ответственности в 
        соответствии со статьей ч. 4 ст. 12.15 КоАП Российской Федерации.
        2. По существу заявления и о принятых мерах направить мотивированный ответ в
        форме электронного документа на адрес %email%. В ответе указать номер интернет-обращения для идентификации ответа.
    </text>
</template>
